{"name":"Anontweets","tagline":"Eggify and anonymize Twitter","body":"\r\nAnon Tweets is a simple Chrome extension. You can find it here: https://chrome.google.com/webstore/detail/anon-tweets/dmpknoegaacimllecbbnabadbacgldba\r\n\r\nThis tiny extension, replaces profile pictures with eggs, hides names and usernames on Twitter. So you can read tweets without knowing who actually wrote them! Just for fun!\r\n\r\n![Screenshot - Timeline](https://raw.githubusercontent.com/humbleai/anontweets/master/screenshot.png)\r\n\r\n\r\n","google":"","note":"Don't delete this file! It's used internally to help with page regeneration."}